mydatatest/__init__.py
mydatatest/calc.py
mydatatest-0.1.dist-info/METADATA
mydatatest-0.1.dist-info/WHEEL
mydatatest-0.1.dist-info/top_level.txt
mydatatest-0.1.dist-info/RECORD
